{"statusCode": 200, "headers": {"Content-Type": "application/json", "Access-Control-Allow-Origin": "*"}, "body": "{\"symbol\": \"AAPL\", \"period\": {\"days\": 30, \"from\": \"2025-12-30T22:45:03.723295\", \"to\": \"2026-01-29T22:45:03.952508\"}, \"statistics\": {\"count\": 6, \"max\": 185.5, \"min\": 182.75, \"avg\": 184.125, \"latest\": 185.5, \"oldest\": 182.75}, \"data\": [{\"timestamp\": 1769720693, \"date\": \"2026-01-29T21:04:53.660938\", \"price\": 185.5, \"volume\": 60000000, \"change\": 4.25}, {\"timestamp\": 1769720662, \"date\": \"2026-01-29T21:04:22.484973\", \"price\": 185.5, \"volume\": 60000000, \"change\": 4.25}, {\"timestamp\": 1769720447, \"date\": \"2026-01-29T21:00:47.662469\", \"price\": 185.5, \"volume\": 60000000, \"change\": 4.25, \"change_percent\": 2.35}, {\"timestamp\": 1769302986, \"date\": \"2026-01-25T01:03:06.101837\", \"price\": 182.75, \"volume\": 58000000, \"change\": 3.25, \"change_percent\": 1.81}, {\"timestamp\": 1769302961, \"date\": \"2026-01-25T01:02:41.724933\", \"price\": 182.75, \"volume\": 58000000, \"change\": 3.25, \"change_percent\": 1.81}, {\"timestamp\": 1769302702, \"date\": \"2026-01-25T00:58:22.397207\", \"price\": 182.75, \"volume\": 58000000, \"change\": 3.25, \"change_percent\": 1.81}], \"message\": \"Hist\\u00f3rico de AAPL obtenido exitosamente\"}"}